kmsr/__init__.py
kmsr/_core.cpp
kmsr/core.py
kmsr/cpp/ball.cpp
kmsr/cpp/cluster.cpp
kmsr/cpp/gonzalez.cpp
kmsr/cpp/heuristic.cpp
kmsr/cpp/k_MSR.cpp
kmsr/cpp/point.cpp
kmsr/cpp/util.cpp
kmsr/cpp/welzl.cpp
kmsr/cpp/yildirim.cpp
kmsr/generate_points.py
kmsr/header/ball.h
kmsr/header/cluster.h
kmsr/header/gonzalez.h
kmsr/header/heuristic.h
kmsr/header/k_MSR.h
kmsr/header/miniball.h
kmsr/header/point.h
kmsr/header/util.h
kmsr/header/welzl.h
kmsr/header/yildirim.h
kmsr/plot.py
kmsr/_core.cpython-310-x86_64-linux-gnu.so
kmsr-0.1.3.dist-info/LICENSE
kmsr-0.1.3.dist-info/METADATA
kmsr-0.1.3.dist-info/WHEEL
kmsr-0.1.3.dist-info/RECORD
