Metadata-Version: 2.1
Name: kmsr
Version: 0.1.3
Summary: kMSR provides a selection of algorithms to solve the k-Min-Sum-Radii problem.
License: LICENSE
Author: Niklas Lenssen
Author-email: niklas.lenssen@hhu.de
Requires-Python: >=3.9,<4.0
Classifier: License :: Other/Proprietary License
Classifier: Programming Language :: Python :: 3
Classifier: Programming Language :: Python :: 3.9
Classifier: Programming Language :: Python :: 3.10
Classifier: Programming Language :: Python :: 3.11
Classifier: Programming Language :: Python :: 3.12
Requires-Dist: scikit-learn (>=1.6.1,<2.0.0)
